yt_ts_extract/__init__.py
yt_ts_extract/cli.py
yt_ts_extract/extractor.py
yt_ts_extract/proxy_manager.py
yt_ts_extract/utils.py
yt_ts_extract-1.0.0.dist-info/METADATA
yt_ts_extract-1.0.0.dist-info/WHEEL
yt_ts_extract-1.0.0.dist-info/entry_points.txt
yt_ts_extract-1.0.0.dist-info/licenses/LICENSE
yt_ts_extract-1.0.0.dist-info/RECORD
