Metadata-Version: 2.4
Name: yt-ts-extract
Version: 1.0.0
Summary: Extract transcripts from YouTube videos with multi-language support and various output formats
Project-URL: Homepage, https://github.com/sinjab/yt-ts-extract
Project-URL: Documentation, https://github.com/sinjab/yt-ts-extract#readme
Project-URL: Repository, https://github.com/sinjab/yt-ts-extract
Project-URL: Issues, https://github.com/sinjab/yt-ts-extract/issues
Author-email: Khaldoon Sinjab <sinjab@gmail.com>
License: MIT License
License-File: LICENSE
Keywords: automation,captions,cli,extract,multilanguage,srt,subtitles,transcript,video,youtube
Classifier: Development Status :: 5 - Production/Stable
Classifier: Intended Audience :: Developers
Classifier: Intended Audience :: End Users/Desktop
Classifier: License :: OSI Approved :: MIT License
Classifier: Operating System :: OS Independent
Classifier: Programming Language :: Python :: 3
Classifier: Programming Language :: Python :: 3.8
Classifier: Programming Language :: Python :: 3.9
Classifier: Programming Language :: Python :: 3.10
Classifier: Programming Language :: Python :: 3.11
Classifier: Programming Language :: Python :: 3.12
Classifier: Topic :: Internet :: WWW/HTTP
Classifier: Topic :: Multimedia :: Video
Classifier: Topic :: Software Development :: Libraries :: Python Modules
Classifier: Topic :: Text Processing
Requires-Python: >=3.8
Requires-Dist: requests>=2.31.0
Provides-Extra: dev
Requires-Dist: black>=22.0.0; extra == 'dev'
Requires-Dist: build>=0.10.0; extra == 'dev'
Requires-Dist: isort>=5.0.0; extra == 'dev'
Requires-Dist: pytest>=7.0.0; extra == 'dev'
Requires-Dist: twine>=4.0.0; extra == 'dev'
